flask_create/__init__.py
flask_create/create.py
flask_create/flask_template/extras/config.py
flask_create/flask_template/extras/scripts.py
flask_create/flask_template/extras/wsgi.py
flask_create/flask_template/src_dir/__init__.py
flask_create/flask_template/src_dir/models.py
flask_create-0.0.2.dist-info/LICENSE
flask_create-0.0.2.dist-info/METADATA
flask_create-0.0.2.dist-info/WHEEL
flask_create-0.0.2.dist-info/entry_points.txt
flask_create-0.0.2.dist-info/top_level.txt
flask_create-0.0.2.dist-info/RECORD
